{
  "alex": {
    "path": "./ai/Alex/alex.py", 
    "score": [
      982, 
      1014, 
      1046, 
      1023, 
      990, 
      1018, 
      1001, 
      1030, 
      1016, 
      1013
    ], 
    "broken": "false"
  }, 
  "annan": {
    "path": "./ai/annan/annan.py", 
    "score": [
      717, 
      858, 
      926, 
      991, 
      989, 
      952, 
      1038, 
      1000, 
      994, 
      940
    ], 
    "broken": "false"
  }, 
  "bb": {
    "path": "./ai/leigao/bb.py", 
    "score": [
      968, 
      1048, 
      1010, 
      1036, 
      1044, 
      949, 
      1001, 
      945, 
      1034, 
      1003
    ], 
    "broken": "false"
  }, 
  "exampleai_cpp": {
    "path": "./ai/example_cpp/exampleaicpp", 
    "score": [
      981, 
      1017, 
      1048, 
      1031, 
      1048, 
      979, 
      1038, 
      982, 
      1058, 
      1020
    ], 
    "broken": "false"
  }, 
  "liux": {
    "path": "./ai/liux/liux.py", 
    "score": [
      990, 
      990, 
      1048, 
      1023, 
      1032, 
      983, 
      1014, 
      1007, 
      1056, 
      1015
    ], 
    "broken": "false"
  }, 
  "dbnai": {
    "path": "./ai/dbnai/dbnai.py", 
    "score": [
      1712, 
      1910, 
      1978, 
      1929, 
      1874, 
      1629, 
      1693, 
      1516, 
      1450, 
      1743
    ], 
    "broken": "false"
  }, 
  "exampleai": {
    "path": "./ai/example/exampleai.py", 
    "score": [
      1000, 
      1000, 
      1000, 
      1000, 
      1000, 
      1000, 
      1000, 
      1000, 
      1000, 
      1000
    ], 
    "broken": "false"
  }, 
  "ai_Claudia": {
    "path": "./ai/ai_Claudia/ai_Claudia.py", 
    "score": [
      1000, 
      1000, 
      1000, 
      1000, 
      1000, 
      1000, 
      1000, 
      1000, 
      1000, 
      1000
    ], 
    "broken": "true"
  }, 
  "Leo": {
    "path": "./ai/Leo/Leo.py", 
    "score": [
      973, 
      1029, 
      1037, 
      1008, 
      1009, 
      984, 
      987, 
      959, 
      1045, 
      1003
    ], 
    "broken": "false"
  }, 
  "Acc404": {
    "path": "./ai/Acc404/Acc404.py", 
    "score": [
      1891, 
      1670, 
      1615, 
      1509, 
      1401, 
      1356, 
      1365, 
      1318, 
      1265, 
      1487
    ], 
    "broken": "false"
  }, 
  "seaky_ai": {
    "path": "./ai/seaky/seaky_ai.py", 
    "score": [
      975, 
      1000, 
      1045, 
      1044, 
      1028, 
      958, 
      996, 
      1001, 
      1058, 
      1011
    ], 
    "broken": "false"
  }, 
  "yuai": {
    "path": "./ai/YuAi/yuai.py", 
    "score": [
      954, 
      1033, 
      996, 
      1019, 
      979, 
      960, 
      1049, 
      1015, 
      1048, 
      1005
    ], 
    "broken": "false"
  }, 
  "seraphroyai": {
    "path": "./ai/seraphroy/seraphroyai.py", 
    "score": [
      956, 
      1019, 
      1062, 
      1043, 
      1027, 
      1009, 
      1029, 
      991, 
      1048, 
      1020
    ], 
    "broken": "false"
  }
}