{
  "alex": {
    "path": "./ai/Alex/alex.py", 
    "score": [
      979, 
      993, 
      1030, 
      972, 
      1047, 
      1114, 
      1027, 
      960, 
      1075, 
      1021
    ], 
    "broken": "false"
  }, 
  "annan": {
    "path": "./ai/annan/annan.py", 
    "score": [
      712, 
      870, 
      931, 
      936, 
      991, 
      1039, 
      1031, 
      1004, 
      1050, 
      951
    ], 
    "broken": "false"
  }, 
  "bb": {
    "path": "./ai/leigao/bb.py", 
    "score": [
      991, 
      1005, 
      989, 
      1001, 
      1015, 
      1033, 
      1026, 
      1036, 
      1042, 
      1015
    ], 
    "broken": "false"
  }, 
  "exampleai_cpp": {
    "path": "./ai/example_cpp/exampleaicpp", 
    "score": [
      964, 
      1040, 
      1007, 
      970, 
      1053, 
      1028, 
      1013, 
      1017, 
      1044, 
      1015
    ], 
    "broken": "false"
  }, 
  "liux": {
    "path": "./ai/liux/liux.py", 
    "score": [
      969, 
      1023, 
      1010, 
      1001, 
      1032, 
      1060, 
      984, 
      987, 
      1040, 
      1011
    ], 
    "broken": "false"
  }, 
  "dbnai": {
    "path": "./ai/dbnai/dbnai.py", 
    "score": [
      1799, 
      1988, 
      2007, 
      1943, 
      1851, 
      1745, 
      1625, 
      1539, 
      1549, 
      1782
    ], 
    "broken": "false"
  }, 
  "exampleai": {
    "path": "./ai/example/exampleai.py", 
    "score": [
      1000, 
      1000, 
      1000, 
      1000, 
      1000, 
      1000, 
      1000, 
      1000, 
      1000, 
      1000
    ], 
    "broken": "false"
  }, 
  "ai_Claudia": {
    "path": "./ai/ai_Claudia/ai_Claudia.py", 
    "score": [
      1000, 
      1000, 
      1000, 
      1000, 
      1000, 
      1000, 
      1000, 
      1000, 
      1000, 
      1000
    ], 
    "broken": "true"
  }, 
  "Leo": {
    "path": "./ai/Leo/Leo.py", 
    "score": [
      985, 
      1050, 
      1060, 
      1014, 
      1077, 
      1028, 
      1014, 
      1050, 
      1032, 
      1034
    ], 
    "broken": "false"
  }, 
  "Acc404": {
    "path": "./ai/Acc404/Acc404.py", 
    "score": [
      2039, 
      1746, 
      1636, 
      1453, 
      1451, 
      1455, 
      1403, 
      1293, 
      1344, 
      1535
    ], 
    "broken": "false"
  }, 
  "seaky_ai": {
    "path": "./ai/seaky/seaky_ai.py", 
    "score": [
      998, 
      1021, 
      1008, 
      987, 
      1047, 
      1052, 
      1034, 
      1000, 
      1022, 
      1018
    ], 
    "broken": "false"
  }, 
  "yuai": {
    "path": "./ai/YuAi/yuai.py", 
    "score": [
      998, 
      1061, 
      993, 
      996, 
      1014, 
      1028, 
      991, 
      1017, 
      1006, 
      1011
    ], 
    "broken": "false"
  }, 
  "seraphroyai": {
    "path": "./ai/seraphroy/seraphroyai.py", 
    "score": [
      1016, 
      1028, 
      970, 
      1050, 
      1062, 
      1006, 
      1001, 
      1011, 
      1060, 
      1022
    ], 
    "broken": "false"
  }
}