{
  "alex": {
    "path": "./ai/Alex/alex.py", 
    "score": [
      976, 
      1022, 
      1027, 
      1006, 
      1021, 
      994, 
      1040, 
      1048, 
      1004, 
      1015
    ], 
    "broken": "false"
  }, 
  "annan": {
    "path": "./ai/annan/annan.py", 
    "score": [
      705, 
      902, 
      910, 
      971, 
      982, 
      1030, 
      1020, 
      1025, 
      960, 
      945
    ], 
    "broken": "false"
  }, 
  "bb": {
    "path": "./ai/leigao/bb.py", 
    "score": [
      984, 
      1034, 
      1013, 
      1003, 
      1022, 
      1028, 
      1015, 
      1010, 
      1008, 
      1013
    ], 
    "broken": "false"
  }, 
  "exampleai_cpp": {
    "path": "./ai/example_cpp/exampleaicpp", 
    "score": [
      983, 
      1027, 
      1004, 
      1016, 
      1033, 
      1031, 
      1022, 
      1065, 
      1018, 
      1022
    ], 
    "broken": "false"
  }, 
  "liux": {
    "path": "./ai/liux/liux.py", 
    "score": [
      980, 
      1022, 
      1003, 
      1024, 
      1044, 
      1030, 
      1033, 
      1062, 
      999, 
      1021
    ], 
    "broken": "false"
  }, 
  "dbnai": {
    "path": "./ai/dbnai/dbnai.py", 
    "score": [
      1785, 
      1946, 
      1975, 
      1977, 
      1742, 
      1706, 
      1585, 
      1538, 
      1426, 
      1742
    ], 
    "broken": "false"
  }, 
  "exampleai": {
    "path": "./ai/example/exampleai.py", 
    "score": [
      1000, 
      1000, 
      1000, 
      1000, 
      1000, 
      1000, 
      1000, 
      1000, 
      1000, 
      1000
    ], 
    "broken": "false"
  }, 
  "ai_Claudia": {
    "path": "./ai/ai_Claudia/ai_Claudia.py", 
    "score": [
      1000, 
      1000, 
      1000, 
      1000, 
      1000, 
      1000, 
      1000, 
      1000, 
      1000, 
      1000
    ], 
    "broken": "true"
  }, 
  "Leo": {
    "path": "./ai/Leo/Leo.py", 
    "score": [
      961, 
      1016, 
      1041, 
      1041, 
      1043, 
      1040, 
      1003, 
      1033, 
      1016, 
      1021
    ], 
    "broken": "false"
  }, 
  "Acc404": {
    "path": "./ai/Acc404/Acc404.py", 
    "score": [
      1970, 
      1763, 
      1607, 
      1511, 
      1416, 
      1355, 
      1340, 
      1320, 
      1293, 
      1508
    ], 
    "broken": "false"
  }, 
  "seaky_ai": {
    "path": "./ai/seaky/seaky_ai.py", 
    "score": [
      1018, 
      1059, 
      1002, 
      1012, 
      1001, 
      1005, 
      974, 
      1033, 
      987, 
      1010
    ], 
    "broken": "false"
  }, 
  "yuai": {
    "path": "./ai/YuAi/yuai.py", 
    "score": [
      979, 
      1021, 
      1006, 
      1074, 
      976, 
      1017, 
      1011, 
      987, 
      1017, 
      1009
    ], 
    "broken": "false"
  }, 
  "seraphroyai": {
    "path": "./ai/seraphroy/seraphroyai.py", 
    "score": [
      990, 
      1008, 
      1019, 
      1002, 
      1011, 
      994, 
      1012, 
      1001, 
      991, 
      1003
    ], 
    "broken": "false"
  }
}