{
  "alex": {
    "path": "./ai/Alex/alex.py", 
    "score": [
      982, 
      1020, 
      1016, 
      983, 
      984, 
      1055, 
      955, 
      1019, 
      995, 
      1001
    ], 
    "broken": "false"
  }, 
  "annan": {
    "path": "./ai/annan/annan.py", 
    "score": [
      719, 
      839, 
      945, 
      947, 
      973, 
      1019, 
      999, 
      1005, 
      976, 
      935
    ], 
    "broken": "false"
  }, 
  "bb": {
    "path": "./ai/leigao/bb.py", 
    "score": [
      974, 
      987, 
      1047, 
      985, 
      983, 
      1003, 
      984, 
      1005, 
      1017, 
      998
    ], 
    "broken": "false"
  }, 
  "exampleai_cpp": {
    "path": "./ai/example_cpp/exampleaicpp", 
    "score": [
      963, 
      1000, 
      1030, 
      1010, 
      982, 
      1061, 
      1008, 
      1049, 
      1049, 
      1016
    ], 
    "broken": "false"
  }, 
  "liux": {
    "path": "./ai/liux/liux.py", 
    "score": [
      982, 
      1035, 
      995, 
      1050, 
      1001, 
      997, 
      1011, 
      986, 
      982, 
      1004
    ], 
    "broken": "false"
  }, 
  "dbnai": {
    "path": "./ai/dbnai/dbnai.py", 
    "score": [
      1730, 
      1990, 
      1901, 
      1847, 
      1862, 
      1703, 
      1526, 
      1574, 
      1477, 
      1734
    ], 
    "broken": "false"
  }, 
  "exampleai": {
    "path": "./ai/example/exampleai.py", 
    "score": [
      1000, 
      1000, 
      1000, 
      1000, 
      1000, 
      1000, 
      1000, 
      1000, 
      1000, 
      1000
    ], 
    "broken": "false"
  }, 
  "ai_Claudia": {
    "path": "./ai/ai_Claudia/ai_Claudia.py", 
    "score": [
      1000, 
      1000, 
      1000, 
      1000, 
      1000, 
      1000, 
      1000, 
      1000, 
      1000, 
      1000
    ], 
    "broken": "true"
  }, 
  "Leo": {
    "path": "./ai/Leo/Leo.py", 
    "score": [
      991, 
      1030, 
      1037, 
      1002, 
      991, 
      998, 
      1017, 
      1071, 
      994, 
      1014
    ], 
    "broken": "false"
  }, 
  "Acc404": {
    "path": "./ai/Acc404/Acc404.py", 
    "score": [
      1857, 
      1725, 
      1643, 
      1494, 
      1478, 
      1401, 
      1394, 
      1342, 
      1264, 
      1510
    ], 
    "broken": "false"
  }, 
  "seaky_ai": {
    "path": "./ai/seaky/seaky_ai.py", 
    "score": [
      971, 
      981, 
      1074, 
      1000, 
      1028, 
      1082, 
      966, 
      1038, 
      1001, 
      1015
    ], 
    "broken": "false"
  }, 
  "yuai": {
    "path": "./ai/YuAi/yuai.py", 
    "score": [
      984, 
      989, 
      1008, 
      1010, 
      1002, 
      1045, 
      998, 
      980, 
      998, 
      1001
    ], 
    "broken": "false"
  }, 
  "seraphroyai": {
    "path": "./ai/seraphroy/seraphroyai.py", 
    "score": [
      966, 
      1009, 
      1012, 
      988, 
      1021, 
      1020, 
      1031, 
      1047, 
      1009, 
      1011
    ], 
    "broken": "false"
  }
}