{
  "alex": {
    "path": "./ai/Alex/alex.py", 
    "score": [
      1000, 
      1000, 
      1000, 
      1000, 
      1000, 
      1000, 
      1000, 
      1000, 
      1000, 
      1000
    ], 
    "broken": "true"
  }, 
  "annan": {
    "path": "./ai/annan/annan.py", 
    "score": [
      1000, 
      1000, 
      1000, 
      1000, 
      1000, 
      1000, 
      1000, 
      1000, 
      1000, 
      1000
    ], 
    "broken": "true"
  }, 
  "bb": {
    "path": "./ai/leigao/bb.py", 
    "score": [
      1002, 
      1014, 
      1016, 
      990, 
      1018, 
      1036, 
      1044, 
      965, 
      975, 
      1006
    ], 
    "broken": "false"
  }, 
  "exampleai_cpp": {
    "path": "./ai/example_cpp/exampleaicpp", 
    "score": [
      999, 
      1012, 
      977, 
      1019, 
      1011, 
      1045, 
      1040, 
      1039, 
      1035, 
      1019
    ], 
    "broken": "false"
  }, 
  "liux": {
    "path": "./ai/liux/liux.py", 
    "score": [
      1012, 
      1013, 
      955, 
      972, 
      967, 
      1028, 
      1031, 
      1026, 
      994, 
      999
    ], 
    "broken": "false"
  }, 
  "dbnai": {
    "path": "./ai/dbnai/dbnai.py", 
    "score": [
      1146, 
      1155, 
      1114, 
      1090, 
      1120, 
      1108, 
      1146, 
      1077, 
      1056, 
      1112
    ], 
    "broken": "false"
  }, 
  "exampleai": {
    "path": "./ai/example/exampleai.py", 
    "score": [
      1000, 
      1000, 
      1000, 
      1000, 
      1000, 
      1000, 
      1000, 
      1000, 
      1000, 
      1000
    ], 
    "broken": "false"
  }, 
  "ai_Claudia": {
    "path": "./ai/ai_Claudia/ai_Claudia.py", 
    "score": [
      1000, 
      1000, 
      1000, 
      1000, 
      1000, 
      1000, 
      1000, 
      1000, 
      1000, 
      1000
    ], 
    "broken": "true"
  }, 
  "Leo": {
    "path": "./ai/Leo/Leo.py", 
    "score": [
      982, 
      1035, 
      965, 
      973, 
      1042, 
      998, 
      1052, 
      1030, 
      975, 
      1005
    ], 
    "broken": "false"
  }, 
  "Acc404": {
    "path": "./ai/Acc404/Acc404.py", 
    "score": [
      1660, 
      1565, 
      1427, 
      1408, 
      1379, 
      1360, 
      1321, 
      1246, 
      1239, 
      1400
    ], 
    "broken": "false"
  }, 
  "seaky_ai": {
    "path": "./ai/seaky/seaky_ai.py", 
    "score": [
      992, 
      985, 
      1007, 
      970, 
      1035, 
      1009, 
      1098, 
      1004, 
      1005, 
      1011
    ], 
    "broken": "false"
  }, 
  "yuai": {
    "path": "./ai/YuAi/yuai.py", 
    "score": [
      951, 
      996, 
      997, 
      953, 
      1013, 
      1009, 
      1084, 
      1001, 
      1030, 
      1003
    ], 
    "broken": "false"
  }, 
  "seraphroyai": {
    "path": "./ai/seraphroy/seraphroyai.py", 
    "score": [
      979, 
      1012, 
      1016, 
      990, 
      1043, 
      1034, 
      1043, 
      990, 
      996, 
      1011
    ], 
    "broken": "false"
  }
}