{
  "alex": {
    "path": "./ai/Alex/alex.py", 
    "score": [
      969, 
      1011, 
      1024, 
      1050, 
      1007, 
      1024, 
      1000, 
      979, 
      1008, 
      1008
    ], 
    "broken": "false"
  }, 
  "annan": {
    "path": "./ai/annan/annan.py", 
    "score": [
      713, 
      872, 
      938, 
      996, 
      988, 
      982, 
      991, 
      997, 
      994, 
      941
    ], 
    "broken": "false"
  }, 
  "bb": {
    "path": "./ai/leigao/bb.py", 
    "score": [
      963, 
      1040, 
      1021, 
      1017, 
      1061, 
      1015, 
      1028, 
      995, 
      1009, 
      1016
    ], 
    "broken": "false"
  }, 
  "exampleai_cpp": {
    "path": "./ai/example_cpp/exampleaicpp", 
    "score": [
      1006, 
      1004, 
      996, 
      1103, 
      1048, 
      983, 
      1029, 
      994, 
      1026, 
      1021
    ], 
    "broken": "false"
  }, 
  "liux": {
    "path": "./ai/liux/liux.py", 
    "score": [
      1001, 
      1038, 
      1010, 
      995, 
      1033, 
      997, 
      1022, 
      1039, 
      1016, 
      1016
    ], 
    "broken": "false"
  }, 
  "dbnai": {
    "path": "./ai/dbnai/dbnai.py", 
    "score": [
      1723, 
      1891, 
      1988, 
      1949, 
      1792, 
      1655, 
      1643, 
      1596, 
      1489, 
      1747
    ], 
    "broken": "false"
  }, 
  "exampleai": {
    "path": "./ai/example/exampleai.py", 
    "score": [
      1000, 
      1000, 
      1000, 
      1000, 
      1000, 
      1000, 
      1000, 
      1000, 
      1000, 
      1000
    ], 
    "broken": "false"
  }, 
  "ai_Claudia": {
    "path": "./ai/ai_Claudia/ai_Claudia.py", 
    "score": [
      1000, 
      1000, 
      1000, 
      1000, 
      1000, 
      1000, 
      1000, 
      1000, 
      1000, 
      1000
    ], 
    "broken": "true"
  }, 
  "Leo": {
    "path": "./ai/Leo/Leo.py", 
    "score": [
      971, 
      1018, 
      1025, 
      1010, 
      1005, 
      1039, 
      1009, 
      988, 
      1037, 
      1011
    ], 
    "broken": "false"
  }, 
  "Acc404": {
    "path": "./ai/Acc404/Acc404.py", 
    "score": [
      1923, 
      1726, 
      1574, 
      1529, 
      1416, 
      1364, 
      1396, 
      1275, 
      1290, 
      1499
    ], 
    "broken": "false"
  }, 
  "seaky_ai": {
    "path": "./ai/seaky/seaky_ai.py", 
    "score": [
      985, 
      1007, 
      1002, 
      1038, 
      1007, 
      1057, 
      998, 
      999, 
      983, 
      1008
    ], 
    "broken": "false"
  }, 
  "yuai": {
    "path": "./ai/YuAi/yuai.py", 
    "score": [
      969, 
      1022, 
      1020, 
      1022, 
      1038, 
      1013, 
      1025, 
      999, 
      1084, 
      1021
    ], 
    "broken": "false"
  }, 
  "seraphroyai": {
    "path": "./ai/seraphroy/seraphroyai.py", 
    "score": [
      979, 
      992, 
      1026, 
      1076, 
      1025, 
      1042, 
      1019, 
      989, 
      1004, 
      1016
    ], 
    "broken": "false"
  }
}