[
    {
        "ANSWER_NUM": 722, 
        "AARATIO": 204.7, 
        "AFRATIO": 4.67, 
        "FOLLOWER": 31660, 
        "FARATIO": 43.85, 
        "AGREE_NUM": 147796, 
        "FOLLOWEE": 0, 
        "NAME": "<a href=\"Hua-Double\uff01\">Hua-Double</a>"
    }, 
    {
        "ANSWER_NUM": 722, 
        "AARATIO": 204.7, 
        "AFRATIO": 4.67, 
        "FOLLOWER": 31660, 
        "FARATIO": 43.85, 
        "AGREE_NUM": 147796, 
        "FOLLOWEE": 0, 
        "NAME": "<a href=\"BenderBendingRodr\u00edguez\">BenderRodriguez</a>"
    }, 
    {
        "ANSWER_NUM": 722, 
        "AARATIO": 204.7, 
        "AFRATIO": 4.67, 
        "FOLLOWER": 31660, 
        "FARATIO": 43.85, 
        "AGREE_NUM": 147796, 
        "FOLLOWEE": 0, 
        "NAME": "<a href=\"\u5149\u660e\">Messiah</a>"
    }, 
    {
        "ANSWER_NUM": 14, 
        "AARATIO": 675.29, 
        "AFRATIO": 1.32, 
        "FOLLOWER": 7137, 
        "FARATIO": 509.79, 
        "AGREE_NUM": 9454, 
        "FOLLOWEE": 95, 
        "NAME": "<a href=\"li-li-nevergg\">\u529b\u529bnevergg</a>"
    }, 
    {
        "ANSWER_NUM": 301, 
        "AARATIO": 90.6, 
        "AFRATIO": 4.19, 
        "FOLLOWER": 6507, 
        "FARATIO": 21.62, 
        "AGREE_NUM": 27271, 
        "FOLLOWEE": 3, 
        "NAME": "<a href=\"hodaat\">\u8377\u8fbe</a>"
    }, 
    {
        "ANSWER_NUM": 144, 
        "AARATIO": 292.81, 
        "AFRATIO": 6.51, 
        "FOLLOWER": 6480, 
        "FARATIO": 45.0, 
        "AGREE_NUM": 42165, 
        "FOLLOWEE": 78, 
        "NAME": "<a href=\"tuyoo\">\u6b8b\u9633\u4f34\u70df\u706b</a>"
    }, 
    {
        "ANSWER_NUM": 75, 
        "AARATIO": 174.2, 
        "AFRATIO": 2.69, 
        "FOLLOWER": 4855, 
        "FARATIO": 64.73, 
        "AGREE_NUM": 13065, 
        "FOLLOWEE": 21, 
        "NAME": "<a href=\"ni-hun-xiao-xiao-sheng\">\u9006\u9b42\u7b11\u7b11\u751f</a>"
    }, 
    {
        "ANSWER_NUM": 39, 
        "AARATIO": 594.51, 
        "AFRATIO": 4.85, 
        "FOLLOWER": 4777, 
        "FARATIO": 122.49, 
        "AGREE_NUM": 23186, 
        "FOLLOWEE": 133, 
        "NAME": "<a href=\"zhao-bu-ming-10\">\u8d75\u4e0d\u660e</a>"
    }, 
    {
        "ANSWER_NUM": 9, 
        "AARATIO": 3176.0, 
        "AFRATIO": 6.01, 
        "FOLLOWER": 4756, 
        "FARATIO": 528.44, 
        "AGREE_NUM": 28584, 
        "FOLLOWEE": 340, 
        "NAME": "<a href=\"jia-jun-hou\">\u8d3e\u73fa</a>"
    }, 
    {
        "ANSWER_NUM": 24, 
        "AARATIO": 544.54, 
        "AFRATIO": 2.81, 
        "FOLLOWER": 4655, 
        "FARATIO": 193.96, 
        "AGREE_NUM": 13069, 
        "FOLLOWEE": 130, 
        "NAME": "<a href=\"wang-ye-80\">\u738b\u4e5f</a>"
    }, 
    {
        "ANSWER_NUM": 144, 
        "AARATIO": 96.87, 
        "AFRATIO": 6.59, 
        "FOLLOWER": 2118, 
        "FARATIO": 14.71, 
        "AGREE_NUM": 13949, 
        "FOLLOWEE": 65, 
        "NAME": "<a href=\"jia-fu-48\">\u846d\u6d6e.PaulLee</a>"
    }, 
    {
        "ANSWER_NUM": 311, 
        "AARATIO": 34.96, 
        "AFRATIO": 5.16, 
        "FOLLOWER": 2107, 
        "FARATIO": 6.77, 
        "AGREE_NUM": 10874, 
        "FOLLOWEE": 422, 
        "NAME": "<a href=\"hai-jun-shang-jiang-hu-de-hao\">\u54aa\u4e86\u4e2a\u55b5</a>"
    }, 
    {
        "ANSWER_NUM": 178, 
        "AARATIO": 21.15, 
        "AFRATIO": 1.93, 
        "FOLLOWER": 1946, 
        "FARATIO": 10.93, 
        "AGREE_NUM": 3765, 
        "FOLLOWEE": 427, 
        "NAME": "<a href=\"chen-xiao-xiao-96-73\">\u674e\u5ae3\u513f</a>"
    }, 
    {
        "ANSWER_NUM": 56, 
        "AARATIO": 123.75, 
        "AFRATIO": 3.61, 
        "FOLLOWER": 1918, 
        "FARATIO": 34.25, 
        "AGREE_NUM": 6930, 
        "FOLLOWEE": 212, 
        "NAME": "<a href=\"zhang-nuo-mei-39\">\u5f20\u5a1c\u7f8e</a>"
    }, 
    {
        "ANSWER_NUM": 65, 
        "AARATIO": 201.63, 
        "AFRATIO": 9.82, 
        "FOLLOWER": 1335, 
        "FARATIO": 20.54, 
        "AGREE_NUM": 13106, 
        "FOLLOWEE": 106, 
        "NAME": "<a href=\"mu-er-71\">\u4e5d\u4e8c</a>"
    }
]